{  
   "forge_marker":1,
   "defaults":{  
      "model":"simplecorn:densecrop",
      "transform":"forge:default-block"
   },
   "variants":{  
      "age":{  
         "0":{  
            "textures":{  
               "crop": "simplecorn:blocks/corn_9"
            }
         },
         "1":{  
            "textures":{  
               "crop": "simplecorn:blocks/corn_12"
            }
         },
         "2":{  
            "textures":{  
               "crop": "simplecorn:blocks/corn_1"
            }
         },
         "3":{  
            "textures":{  
               "crop": "simplecorn:blocks/corn_1"
            }
         },
         "4":{  
            "textures":{  
               "crop": "simplecorn:blocks/corn_1"
            }
         },
         "5":{  
            "textures":{  
               "crop": "simplecorn:blocks/corn_1"
            }
         }
      }
   }
}